Metadata-Version: 2.1
Name: Virus-Total-Bypass
Version: 0.0.6
Summary: Script made in python to try to have as few detections as possible in Virustotal.
Home-page: https://github.com/CookiesKush
Author: CookiesKush420
Author-email: cookiesservices@triots.com
License: MIT
Keywords: Virus Total,Bypass
Platform: UNKNOWN
Classifier: Development Status :: 4 - Beta
Classifier: Intended Audience :: Developers
Classifier: Operating System :: Microsoft :: Windows :: Windows 10
Classifier: License :: OSI Approved :: MIT License
Classifier: Programming Language :: Python :: 3 :: Only
License-File: LICENCE.txt
